README.md
setup.py
examples/NA.py
examples/allemand.py
examples/antipatterns.py
examples/classifier.py
examples/greenberg_25.py
examples/request_frequency.py
examples/test_Fs_edge.py
examples/test_GRS.py
examples/test_corpus.py
examples/test_graph.py
examples/test_grew_web.py
examples/test_named_entities.py
examples/test_request.py
examples/test_search.py
grewpy/__init__.py
grewpy/corpus.py
grewpy/graph.py
grewpy/grew.py
grewpy/grew_web.py
grewpy/grs.py
grewpy/matchings.py
grewpy/network.py
grewpy/observation.py
grewpy/sketch.py
grewpy/utils.py
grewpy.egg-info/PKG-INFO
grewpy.egg-info/SOURCES.txt
grewpy.egg-info/dependency_links.txt
grewpy.egg-info/requires.txt
grewpy.egg-info/top_level.txt