Metadata-Version: 2.1
Name: grewpy
Version: 0.6.0
Summary: A binding to the Grew software
Home-page: https://grew.fr
Author: bguil
Author-email: Bruno.Guillaume@loria.fr
License: LICENSE/Licence_CeCILL_V2-en.txt
Platform: UNKNOWN
